LICENSE
MANIFEST.in
README.rst
setup.py
tests.py
FeinCMS_Code.egg-info/PKG-INFO
FeinCMS_Code.egg-info/SOURCES.txt
FeinCMS_Code.egg-info/dependency_links.txt
FeinCMS_Code.egg-info/requires.txt
FeinCMS_Code.egg-info/top_level.txt
feincms_code/__init__.py
feincms_code/content.py
feincms_code/models.py
feincms_code/templates/content/code.html