Metadata-Version: 1.0
Name: FeinCMS-Code
Version: 0.0.2
Summary: Pygments formatter content type for FeinCMS.
Home-page: https://github.com/RichardOfWard/feincms-code
Author: Richard Ward
Author-email: richard@richard.ward.name
License: MIT
Platform: UNKNOWN
